Verilog Code/miniproject.v
module speed(clk,reset,result);
  input clk,reset;
  output [8:0]result;
  reg [8:0] spe;
  always @(posedge clk or posedge reset) begin
    if (reset) begin
      spe <= 9'b0;
    end else begin
      spe <= spe + 18;
    end

  end
  assign result = spe;

endmodule

module distance(clk,reset2,result);
  input clk,reset2;
  output [12:0]result;
  reg [12:0]dist;
  always @(posedge clk or posedge reset2) begin
    if (reset2) begin
      dist <= 13'b0;
    end else begin
      dist <= dist + 5;
    end
  end
  assign result = dist;
endmodule

Verilog Code/miniproject_tb.v
module miniproject_tb;

  reg clk;        
  reg reset,reset2;       
  wire [8:0] result1;
  wire [12:0] result2; 

  speed M1(clk,reset,result1);
  distance M2(clk,reset2,result2);
  // Assuming hall effect sensor as a clock with 100Hz frequency
  always begin
    #5 clk = ~clk;
  end
  initial begin
    #5 reset2=~reset2;
    #5 reset2=~reset2;
    #5 reset=~reset;
    #5 reset=~reset;
  end
  // Reset value (1 Hz)
  always begin
    #500 reset = ~reset;
    #5 reset= ~reset;
  end
  
  initial begin
    $display("Time,Speed,Distance");
    $monitor("%d, %b %b", $time,result1,result2);
    #10000 $finish;
  end

  initial begin
    clk = 0;
    reset = 0;
    reset2=0;
  end

endmodule

Verilog Code/miniproject.vcd
$date
	Thu Nov 02 18:58:25 2023
$end
$version
	Icarus Verilog
$end
$timescale
	1s
$end
$scope module miniproject_tb $end
$var wire 13 ! result2 [12:0] $end
$var wire 9 " result1 [8:0] $end
$var reg 1 # clk $end
$var reg 1 $ reset $end
$var reg 1 % reset2 $end
$scope module M1 $end
$var wire 1 # clk $end
$var wire 1 $ reset $end
$var wire 9 & result [8:0] $end
$var reg 9 ' spe [8:0] $end
$upscope $end
$scope module M2 $end
$var wire 1 # clk $end
$var wire 1 % reset2 $end
$var wire 13 ( result [12:0] $end
$var reg 13 ) dist [12:0] $end
$upscope $end
$upscope $end
$enddefinitions $end
$comment Show the parameter values. $end
$dumpall
$end
#0
$dumpvars
bx )
bx (
bx '
bx &
0%
0$
0#
bx "
bx !
$end
#5
b0 !
b0 (
b0 )
1%
1#
#10
0%
0#
#15
b0 "
b0 &
b0 '
b101 !
b101 (
b101 )
1$
1#
#20
0$
0#
#25
b10010 "
b10010 &
b10010 '
b1010 !
b1010 (
b1010 )
1#
#30
0#
#35
b100100 "
b100100 &
b100100 '
b1111 !
b1111 (
b1111 )
1#
#40
0#
#45
b110110 "
b110110 &
b110110 '
b10100 !
b10100 (
b10100 )
1#
#50
0#
#55
b1001000 "
b1001000 &
b1001000 '
b11001 !
b11001 (
b11001 )
1#
#60
0#
#65
b1011010 "
b1011010 &
b1011010 '
b11110 !
b11110 (
b11110 )
1#
#70
0#
#75
b1101100 "
b1101100 &
b1101100 '
b100011 !
b100011 (
b100011 )
1#
#80
0#
#85
b1111110 "
b1111110 &
b1111110 '
b101000 !
b101000 (
b101000 )
1#
#90
0#
#95
b10010000 "
b10010000 &
b10010000 '
b101101 !
b101101 (
b101101 )
1#
#100
0#
#105
b10100010 "
b10100010 &
b10100010 '
b110010 !
b110010 (
b110010 )
1#
#110
0#
#115
b10110100 "
b10110100 &
b10110100 '
b110111 !
b110111 (
b110111 )
1#
#120
0#
#125
b11000110 "
b11000110 &
b11000110 '
b111100 !
b111100 (
b111100 )
1#
#130
0#
#135
b11011000 "
b11011000 &
b11011000 '
b1000001 !
b1000001 (
b1000001 )
1#
#140
0#
#145
b11101010 "
b11101010 &
b11101010 '
b1000110 !
b1000110 (
b1000110 )
1#
#150
0#
#155
b11111100 "
b11111100 &
b11111100 '
b1001011 !
b1001011 (
b1001011 )
1#
#160
0#
#165
b100001110 "
b100001110 &
b100001110 '
b1010000 !
b1010000 (
b1010000 )
1#
#170
0#
#175
b100100000 "
b100100000 &
b100100000 '
b1010101 !
b1010101 (
b1010101 )
1#
#180
0#
#185
b100110010 "
b100110010 &
b100110010 '
b1011010 !
b1011010 (
b1011010 )
1#
#190
0#
#195
b101000100 "
b101000100 &
b101000100 '
b1011111 !
b1011111 (
b1011111 )
1#
#200
0#
#205
b101010110 "
b101010110 &
b101010110 '
b1100100 !
b1100100 (
b1100100 )
1#
#210
0#
#215
b101101000 "
b101101000 &
b101101000 '
b1101001 !
b1101001 (
b1101001 )
1#
#220
0#
#225
b101111010 "
b101111010 &
b101111010 '
b1101110 !
b1101110 (
b1101110 )
1#
#230
0#
#235
b110001100 "
b110001100 &
b110001100 '
b1110011 !
b1110011 (
b1110011 )
1#
#240
0#
#245
b110011110 "
b110011110 &
b110011110 '
b1111000 !
b1111000 (
b1111000 )
1#
#250
0#
#255
b110110000 "
b110110000 &
b110110000 '
b1111101 !
b1111101 (
b1111101 )
1#
#260
0#
#265
b111000010 "
b111000010 &
b111000010 '
b10000010 !
b10000010 (
b10000010 )
1#
#270
0#
#275
b111010100 "
b111010100 &
b111010100 '
b10000111 !
b10000111 (
b10000111 )
1#
#280
0#
#285
b111100110 "
b111100110 &
b111100110 '
b10001100 !
b10001100 (
b10001100 )
1#
#290
0#
#295
b111111000 "
b111111000 &
b111111000 '
b10010001 !
b10010001 (
b10010001 )
1#
#300
0#
#305
b1010 "
b1010 &
b1010 '
b10010110 !
b10010110 (
b10010110 )
1#
#310
0#
#315
b11100 "
b11100 &
b11100 '
b10011011 !
b10011011 (
b10011011 )
1#
#320
0#
#325
b101110 "
b101110 &
b101110 '
b10100000 !
b10100000 (
b10100000 )
1#
#330
0#
#335
b1000000 "
b1000000 &
b1000000 '
b10100101 !
b10100101 (
b10100101 )
1#
#340
0#
#345
b1010010 "
b1010010 &
b1010010 '
b10101010 !
b10101010 (
b10101010 )
1#
#350
0#
#355
b1100100 "
b1100100 &
b1100100 '
b10101111 !
b10101111 (
b10101111 )
1#
#360
0#
#365
b1110110 "
b1110110 &
b1110110 '
b10110100 !
b10110100 (
b10110100 )
1#
#370
0#
#375
b10001000 "
b10001000 &
b10001000 '
b10111001 !
b10111001 (
b10111001 )
1#
#380
0#
#385
b10011010 "
b10011010 &
b10011010 '
b10111110 !
b10111110 (
b10111110 )
1#
#390
0#
#395
b10101100 "
b10101100 &
b10101100 '
b11000011 !
b11000011 (
b11000011 )
1#
#400
0#
#405
b10111110 "
b10111110 &
b10111110 '
b11001000 !
b11001000 (
b11001000 )
1#
#410
0#
#415
b11010000 "
b11010000 &
b11010000 '
b11001101 !
b11001101 (
b11001101 )
1#
#420
0#
#425
b11100010 "
b11100010 &
b11100010 '
b11010010 !
b11010010 (
b11010010 )
1#
#430
0#
#435
b11110100 "
b11110100 &
b11110100 '
b11010111 !
b11010111 (
b11010111 )
1#
#440
0#
#445
b100000110 "
b100000110 &
b100000110 '
b11011100 !
b11011100 (
b11011100 )
1#
#450
0#
#455
b100011000 "
b100011000 &
b100011000 '
b11100001 !
b11100001 (
b11100001 )
1#
#460
0#
#465
b100101010 "
b100101010 &
b100101010 '
b11100110 !
b11100110 (
b11100110 )
1#
#470
0#
#475
b100111100 "
b100111100 &
b100111100 '
b11101011 !
b11101011 (
b11101011 )
1#
#480
0#
#485
b101001110 "
b101001110 &
b101001110 '
b11110000 !
b11110000 (
b11110000 )
1#
#490
0#
#495
b101100000 "
b101100000 &
b101100000 '
b11110101 !
b11110101 (
b11110101 )
1#
#500
b0 "
b0 &
b0 '
0#
1$
#505
b10010 "
b10010 &
b10010 '
b11111010 !
b11111010 (
b11111010 )
1#
0$
#510
0#
#515
b100100 "
b100100 &
b100100 '
b11111111 !
b11111111 (
b11111111 )
1#
#520
0#
#525
b110110 "
b110110 &
b110110 '
b100000100 !
b100000100 (
b100000100 )
1#
#530
0#
#535
b1001000 "
b1001000 &
b1001000 '
b100001001 !
b100001001 (
b100001001 )
1#
#540
0#
#545
b1011010 "
b1011010 &
b1011010 '
b100001110 !
b100001110 (
b100001110 )
1#
#550
0#
#555
b1101100 "
b1101100 &
b1101100 '
b100010011 !
b100010011 (
b100010011 )
1#
#560
0#
#565
b1111110 "
b1111110 &
b1111110 '
b100011000 !
b100011000 (
b100011000 )
1#
#570
0#
#575
b10010000 "
b10010000 &
b10010000 '
b100011101 !
b100011101 (
b100011101 )
1#
#580
0#
#585
b10100010 "
b10100010 &
b10100010 '
b100100010 !
b100100010 (
b100100010 )
1#
#590
0#
#595
b10110100 "
b10110100 &
b10110100 '
b100100111 !
b100100111 (
b100100111 )
1#
#600
0#
#605
b11000110 "
b11000110 &
b11000110 '
b100101100 !
b100101100 (
b100101100 )
1#
#610
0#
#615
b11011000 "
b11011000 &
b11011000 '
b100110001 !
b100110001 (
b100110001 )
1#
#620
0#
#625
b11101010 "
b11101010 &
b11101010 '
b100110110 !
b100110110 (
b100110110 )
1#
#630
0#
#635
b11111100 "
b11111100 &
b11111100 '
b100111011 !
b100111011 (
b100111011 )
1#
#640
0#
#645
b100001110 "
b100001110 &
b100001110 '
b101000000 !
b101000000 (
b101000000 )
1#
#650
0#
#655
b100100000 "
b100100000 &
b100100000 '
b101000101 !
b101000101 (
b101000101 )
1#
#660
0#
#665
b100110010 "
b100110010 &
b100110010 '
b101001010 !
b101001010 (
b101001010 )
1#
#670
0#
#675
b101000100 "
b101000100 &
b101000100 '
b101001111 !
b101001111 (
b101001111 )
1#
#680
0#
#685
b101010110 "
b101010110 &
b101010110 '
b101010100 !
b101010100 (
b101010100 )
1#
#690
0#
#695
b101101000 "
b101101000 &
b101101000 '
b101011001 !
b101011001 (
b101011001 )
1#
#700
0#
#705
b101111010 "
b101111010 &
b101111010 '
b101011110 !
b101011110 (
b101011110 )
1#
#710
0#
#715
b110001100 "
b110001100 &
b110001100 '
b101100011 !
b101100011 (
b101100011 )
1#
#720
0#
#725
b110011110 "
b110011110 &
b110011110 '
b101101000 !
b101101000 (
b101101000 )
1#
#730
0#
#735
b110110000 "
b110110000 &
b110110000 '
b101101101 !
b101101101 (
b101101101 )
1#
#740
0#
#745
b111000010 "
b111000010 &
b111000010 '
b101110010 !
b101110010 (
b101110010 )
1#
#750
0#
#755
b111010100 "
b111010100 &
b111010100 '
b101110111 !
b101110111 (
b101110111 )
1#
#760
0#
#765
b111100110 "
b111100110 &
b111100110 '
b101111100 !
b101111100 (
b101111100 )
1#
#770
0#
#775
b111111000 "
b111111000 &
b111111000 '
b110000001 !
b110000001 (
b110000001 )
1#
#780
0#
#785
b1010 "
b1010 &
b1010 '
b110000110 !
b110000110 (
b110000110 )
1#
#790
0#
#795
b11100 "
b11100 &
b11100 '
b110001011 !
b110001011 (
b110001011 )
1#
#800
0#
#805
b101110 "
b101110 &
b101110 '
b110010000 !
b110010000 (
b110010000 )
1#
#810
0#
#815
b1000000 "
b1000000 &
b1000000 '
b110010101 !
b110010101 (
b110010101 )
1#
#820
0#
#825
b1010010 "
b1010010 &
b1010010 '
b110011010 !
b110011010 (
b110011010 )
1#
#830
0#
#835
b1100100 "
b1100100 &
b1100100 '
b110011111 !
b110011111 (
b110011111 )
1#
#840
0#
#845
b1110110 "
b1110110 &
b1110110 '
b110100100 !
b110100100 (
b110100100 )
1#
#850
0#
#855
b10001000 "
b10001000 &
b10001000 '
b110101001 !
b110101001 (
b110101001 )
1#
#860
0#
#865
b10011010 "
b10011010 &
b10011010 '
b110101110 !
b110101110 (
b110101110 )
1#
#870
0#
#875
b10101100 "
b10101100 &
b10101100 '
b110110011 !
b110110011 (
b110110011 )
1#
#880
0#
#885
b10111110 "
b10111110 &
b10111110 '
b110111000 !
b110111000 (
b110111000 )
1#
#890
0#
#895
b11010000 "
b11010000 &
b11010000 '
b110111101 !
b110111101 (
b110111101 )
1#
#900
0#
#905
b11100010 "
b11100010 &
b11100010 '
b111000010 !
b111000010 (
b111000010 )
1#
#910
0#
#915
b11110100 "
b11110100 &
b11110100 '
b111000111 !
b111000111 (
b111000111 )
1#
#920
0#
#925
b100000110 "
b100000110 &
b100000110 '
b111001100 !
b111001100 (
b111001100 )
1#
#930
0#
#935
b100011000 "
b100011000 &
b100011000 '
b111010001 !
b111010001 (
b111010001 )
1#
#940
0#
#945
b100101010 "
b100101010 &
b100101010 '
b111010110 !
b111010110 (
b111010110 )
1#
#950
0#
#955
b100111100 "
b100111100 &
b100111100 '
b111011011 !
b111011011 (
b111011011 )
1#
#960
0#
#965
b101001110 "
b101001110 &
b101001110 '
b111100000 !
b111100000 (
b111100000 )
1#
#970
0#
#975
b101100000 "
b101100000 &
b101100000 '
b111100101 !
b111100101 (
b111100101 )
1#
#980
0#
#985
b101110010 "
b101110010 &
b101110010 '
b111101010 !
b111101010 (
b111101010 )
1#
#990
0#
#995
b110000100 "
b110000100 &
b110000100 '
b111101111 !
b111101111 (
b111101111 )
1#
#1000
0#
#1005
b111110100 !
b111110100 (
b111110100 )
b0 "
b0 &
b0 '
1#
1$
#1010
0#
0$
#1015
b10010 "
b10010 &
b10010 '
b111111001 !
b111111001 (
b111111001 )
1#
#1020
0#
#1025
b100100 "
b100100 &
b100100 '
b111111110 !
b111111110 (
b111111110 )
1#
#1030
0#
#1035
b110110 "
b110110 &
b110110 '
b1000000011 !
b1000000011 (
b1000000011 )
1#
#1040
0#
#1045
b1001000 "
b1001000 &
b1001000 '
b1000001000 !
b1000001000 (
b1000001000 )
1#
#1050
0#
#1055
b1011010 "
b1011010 &
b1011010 '
b1000001101 !
b1000001101 (
b1000001101 )
1#
#1060
0#
#1065
b1101100 "
b1101100 &
b1101100 '
b1000010010 !
b1000010010 (
b1000010010 )
1#
#1070
0#
#1075
b1111110 "
b1111110 &
b1111110 '
b1000010111 !
b1000010111 (
b1000010111 )
1#
#1080
0#
#1085
b10010000 "
b10010000 &
b10010000 '
b1000011100 !
b1000011100 (
b1000011100 )
1#
#1090
0#
#1095
b10100010 "
b10100010 &
b10100010 '
b1000100001 !
b1000100001 (
b1000100001 )
1#
#1100
0#
#1105
b10110100 "
b10110100 &
b10110100 '
b1000100110 !
b1000100110 (
b1000100110 )
1#
#1110
0#
#1115
b11000110 "
b11000110 &
b11000110 '
b1000101011 !
b1000101011 (
b1000101011 )
1#
#1120
0#
#1125
b11011000 "
b11011000 &
b11011000 '
b1000110000 !
b1000110000 (
b1000110000 )
1#
#1130
0#
#1135
b11101010 "
b11101010 &
b11101010 '
b1000110101 !
b1000110101 (
b1000110101 )
1#
#1140
0#
#1145
b11111100 "
b11111100 &
b11111100 '
b1000111010 !
b1000111010 (
b1000111010 )
1#
#1150
0#
#1155
b100001110 "
b100001110 &
b100001110 '
b1000111111 !
b1000111111 (
b1000111111 )
1#
#1160
0#
#1165
b100100000 "
b100100000 &
b100100000 '
b1001000100 !
b1001000100 (
b1001000100 )
1#
#1170
0#
#1175
b100110010 "
b100110010 &
b100110010 '
b1001001001 !
b1001001001 (
b1001001001 )
1#
#1180
0#
#1185
b101000100 "
b101000100 &
b101000100 '
b1001001110 !
b1001001110 (
b1001001110 )
1#
#1190
0#
#1195
b101010110 "
b101010110 &
b101010110 '
b1001010011 !
b1001010011 (
b1001010011 )
1#
#1200
0#
#1205
b101101000 "
b101101000 &
b101101000 '
b1001011000 !
b1001011000 (
b1001011000 )
1#
#1210
0#
#1215
b101111010 "
b101111010 &
b101111010 '
b1001011101 !
b1001011101 (
b1001011101 )
1#
#1220
0#
#1225
b110001100 "
b110001100 &
b110001100 '
b1001100010 !
b1001100010 (
b1001100010 )
1#
#1230
0#
#1235
b110011110 "
b110011110 &
b110011110 '
b1001100111 !
b1001100111 (
b1001100111 )
1#
#1240
0#
#1245
b110110000 "
b110110000 &
b110110000 '
b1001101100 !
b1001101100 (
b1001101100 )
1#
#1250
0#
#1255
b111000010 "
b111000010 &
b111000010 '
b1001110001 !
b1001110001 (
b1001110001 )
1#
#1260
0#
#1265
b111010100 "
b111010100 &
b111010100 '
b1001110110 !
b1001110110 (
b1001110110 )
1#
#1270
0#
#1275
b111100110 "
b111100110 &
b111100110 '
b1001111011 !
b1001111011 (
b1001111011 )
1#
#1280
0#
#1285
b111111000 "
b111111000 &
b111111000 '
b1010000000 !
b1010000000 (
b1010000000 )
1#
#1290
0#
#1295
b1010 "
b1010 &
b1010 '
b1010000101 !
b1010000101 (
b1010000101 )
1#
#1300
0#
#1305
b11100 "
b11100 &
b11100 '
b1010001010 !
b1010001010 (
b1010001010 )
1#
#1310
0#
#1315
b101110 "
b101110 &
b101110 '
b1010001111 !
b1010001111 (
b1010001111 )
1#
#1320
0#
#1325
b1000000 "
b1000000 &
b1000000 '
b1010010100 !
b1010010100 (
b1010010100 )
1#
#1330
0#
#1335
b1010010 "
b1010010 &
b1010010 '
b1010011001 !
b1010011001 (
b1010011001 )
1#
#1340
0#
#1345
b1100100 "
b1100100 &
b1100100 '
b1010011110 !
b1010011110 (
b1010011110 )
1#
#1350
0#
#1355
b1110110 "
b1110110 &
b1110110 '
b1010100011 !
b1010100011 (
b1010100011 )
1#
#1360
0#
#1365
b10001000 "
b10001000 &
b10001000 '
b1010101000 !
b1010101000 (
b1010101000 )
1#
#1370
0#
#1375
b10011010 "
b10011010 &
b10011010 '
b1010101101 !
b1010101101 (
b1010101101 )
1#
#1380
0#
#1385
b10101100 "
b10101100 &
b10101100 '
b1010110010 !
b1010110010 (
b1010110010 )
1#
#1390
0#
#1395
b10111110 "
b10111110 &
b10111110 '
b1010110111 !
b1010110111 (
b1010110111 )
1#
#1400
0#
#1405
b11010000 "
b11010000 &
b11010000 '
b1010111100 !
b1010111100 (
b1010111100 )
1#
#1410
0#
#1415
b11100010 "
b11100010 &
b11100010 '
b1011000001 !
b1011000001 (
b1011000001 )
1#
#1420
0#
#1425
b11110100 "
b11110100 &
b11110100 '
b1011000110 !
b1011000110 (
b1011000110 )
1#
#1430
0#
#1435
b100000110 "
b100000110 &
b100000110 '
b1011001011 !
b1011001011 (
b1011001011 )
1#
#1440
0#
#1445
b100011000 "
b100011000 &
b100011000 '
b1011010000 !
b1011010000 (
b1011010000 )
1#
#1450
0#
#1455
b100101010 "
b100101010 &
b100101010 '
b1011010101 !
b1011010101 (
b1011010101 )
1#
#1460
0#
#1465
b100111100 "
b100111100 &
b100111100 '
b1011011010 !
b1011011010 (
b1011011010 )
1#
#1470
0#
#1475
b101001110 "
b101001110 &
b101001110 '
b1011011111 !
b1011011111 (
b1011011111 )
1#
#1480
0#
#1485
b101100000 "
b101100000 &
b101100000 '
b1011100100 !
b1011100100 (
b1011100100 )
1#
#1490
0#
#1495
b101110010 "
b101110010 &
b101110010 '
b1011101001 !
b1011101001 (
b1011101001 )
1#
#1500
0#
#1505
b110000100 "
b110000100 &
b110000100 '
b1011101110 !
b1011101110 (
b1011101110 )
1#
#1510
b0 "
b0 &
b0 '
0#
1$
#1515
b10010 "
b10010 &
b10010 '
b1011110011 !
b1011110011 (
b1011110011 )
1#
0$
#1520
0#
#1525
b100100 "
b100100 &
b100100 '
b1011111000 !
b1011111000 (
b1011111000 )
1#
#1530
0#
#1535
b110110 "
b110110 &
b110110 '
b1011111101 !
b1011111101 (
b1011111101 )
1#
#1540
0#
#1545
b1001000 "
b1001000 &
b1001000 '
b1100000010 !
b1100000010 (
b1100000010 )
1#
#1550
0#
#1555
b1011010 "
b1011010 &
b1011010 '
b1100000111 !
b1100000111 (
b1100000111 )
1#
#1560
0#
#1565
b1101100 "
b1101100 &
b1101100 '
b1100001100 !
b1100001100 (
b1100001100 )
1#
#1570
0#
#1575
b1111110 "
b1111110 &
b1111110 '
b1100010001 !
b1100010001 (
b1100010001 )
1#
#1580
0#
#1585
b10010000 "
b10010000 &
b10010000 '
b1100010110 !
b1100010110 (
b1100010110 )
1#
#1590
0#
#1595
b10100010 "
b10100010 &
b10100010 '
b1100011011 !
b1100011011 (
b1100011011 )
1#
#1600
0#
#1605
b10110100 "
b10110100 &
b10110100 '
b1100100000 !
b1100100000 (
b1100100000 )
1#
#1610
0#
#1615
b11000110 "
b11000110 &
b11000110 '
b1100100101 !
b1100100101 (
b1100100101 )
1#
#1620
0#
#1625
b11011000 "
b11011000 &
b11011000 '
b1100101010 !
b1100101010 (
b1100101010 )
1#
#1630
0#
#1635
b11101010 "
b11101010 &
b11101010 '
b1100101111 !
b1100101111 (
b1100101111 )
1#
#1640
0#
#1645
b11111100 "
b11111100 &
b11111100 '
b1100110100 !
b1100110100 (
b1100110100 )
1#
#1650
0#
#1655
b100001110 "
b100001110 &
b100001110 '
b1100111001 !
b1100111001 (
b1100111001 )
1#
#1660
0#
#1665
b100100000 "
b100100000 &
b100100000 '
b1100111110 !
b1100111110 (
b1100111110 )
1#
#1670
0#
#1675
b100110010 "
b100110010 &
b100110010 '
b1101000011 !
b1101000011 (
b1101000011 )
1#
#1680
0#
#1685
b101000100 "
b101000100 &
b101000100 '
b1101001000 !
b1101001000 (
b1101001000 )
1#
#1690
0#
#1695
b101010110 "
b101010110 &
b101010110 '
b1101001101 !
b1101001101 (
b1101001101 )
1#
#1700
0#
#1705
b101101000 "
b101101000 &
b101101000 '
b1101010010 !
b1101010010 (
b1101010010 )
1#
#1710
0#
#1715
b101111010 "
b101111010 &
b101111010 '
b1101010111 !
b1101010111 (
b1101010111 )
1#
#1720
0#
#1725
b110001100 "
b110001100 &
b110001100 '
b1101011100 !
b1101011100 (
b1101011100 )
1#
#1730
0#
#1735
b110011110 "
b110011110 &
b110011110 '
b1101100001 !
b1101100001 (
b1101100001 )
1#
#1740
0#
#1745
b110110000 "
b110110000 &
b110110000 '
b1101100110 !
b1101100110 (
b1101100110 )
1#
#1750
0#
#1755
b111000010 "
b111000010 &
b111000010 '
b1101101011 !
b1101101011 (
b1101101011 )
1#
#1760
0#
#1765
b111010100 "
b111010100 &
b111010100 '
b1101110000 !
b1101110000 (
b1101110000 )
1#
#1770
0#
#1775
b111100110 "
b111100110 &
b111100110 '
b1101110101 !
b1101110101 (
b1101110101 )
1#
#1780
0#
#1785
b111111000 "
b111111000 &
b111111000 '
b1101111010 !
b1101111010 (
b1101111010 )
1#
#1790
0#
#1795
b1010 "
b1010 &
b1010 '
b1101111111 !
b1101111111 (
b1101111111 )
1#
#1800
0#
#1805
b11100 "
b11100 &
b11100 '
b1110000100 !
b1110000100 (
b1110000100 )
1#
#1810
0#
#1815
b101110 "
b101110 &
b101110 '
b1110001001 !
b1110001001 (
b1110001001 )
1#
#1820
0#
#1825
b1000000 "
b1000000 &
b1000000 '
b1110001110 !
b1110001110 (
b1110001110 )
1#
#1830
0#
#1835
b1010010 "
b1010010 &
b1010010 '
b1110010011 !
b1110010011 (
b1110010011 )
1#
#1840
0#
#1845
b1100100 "
b1100100 &
b1100100 '
b1110011000 !
b1110011000 (
b1110011000 )
1#
#1850
0#
#1855
b1110110 "
b1110110 &
b1110110 '
b1110011101 !
b1110011101 (
b1110011101 )
1#
#1860
0#
#1865
b10001000 "
b10001000 &
b10001000 '
b1110100010 !
b1110100010 (
b1110100010 )
1#
#1870
0#
#1875
b10011010 "
b10011010 &
b10011010 '
b1110100111 !
b1110100111 (
b1110100111 )
1#
#1880
0#
#1885
b10101100 "
b10101100 &
b10101100 '
b1110101100 !
b1110101100 (
b1110101100 )
1#
#1890
0#
#1895
b10111110 "
b10111110 &
b10111110 '
b1110110001 !
b1110110001 (
b1110110001 )
1#
#1900
0#
#1905
b11010000 "
b11010000 &
b11010000 '
b1110110110 !
b1110110110 (
b1110110110 )
1#
#1910
0#
#1915
b11100010 "
b11100010 &
b11100010 '
b1110111011 !
b1110111011 (
b1110111011 )
1#
#1920
0#
#1925
b11110100 "
b11110100 &
b11110100 '
b1111000000 !
b1111000000 (
b1111000000 )
1#
#1930
0#
#1935
b100000110 "
b100000110 &
b100000110 '
b1111000101 !
b1111000101 (
b1111000101 )
1#
#1940
0#
#1945
b100011000 "
b100011000 &
b100011000 '
b1111001010 !
b1111001010 (
b1111001010 )
1#
#1950
0#
#1955
b100101010 "
b100101010 &
b100101010 '
b1111001111 !
b1111001111 (
b1111001111 )
1#
#1960
0#
#1965
b100111100 "
b100111100 &
b100111100 '
b1111010100 !
b1111010100 (
b1111010100 )
1#
#1970
0#
#1975
b101001110 "
b101001110 &
b101001110 '
b1111011001 !
b1111011001 (
b1111011001 )
1#
#1980
0#
#1985
b101100000 "
b101100000 &
b101100000 '
b1111011110 !
b1111011110 (
b1111011110 )
1#
#1990
0#
#1995
b101110010 "
b101110010 &
b101110010 '
b1111100011 !
b1111100011 (
b1111100011 )
1#
#2000
0#
#2005
b110000100 "
b110000100 &
b110000100 '
b1111101000 !
b1111101000 (
b1111101000 )
1#
#2010
0#
#2015
b1111101101 !
b1111101101 (
b1111101101 )
b0 "
b0 &
b0 '
1#
1$
#2020
0#
0$
#2025
b10010 "
b10010 &
b10010 '
b1111110010 !
b1111110010 (
b1111110010 )
1#
#2030
0#
#2035
b100100 "
b100100 &
b100100 '
b1111110111 !
b1111110111 (
b1111110111 )
1#
#2040
0#
#2045
b110110 "
b110110 &
b110110 '
b1111111100 !
b1111111100 (
b1111111100 )
1#
#2050
0#
#2055
b1001000 "
b1001000 &
b1001000 '
b10000000001 !
b10000000001 (
b10000000001 )
1#
#2060
0#
#2065
b1011010 "
b1011010 &
b1011010 '
b10000000110 !
b10000000110 (
b10000000110 )
1#
#2070
0#
#2075
b1101100 "
b1101100 &
b1101100 '
b10000001011 !
b10000001011 (
b10000001011 )
1#
#2080
0#
#2085
b1111110 "
b1111110 &
b1111110 '
b10000010000 !
b10000010000 (
b10000010000 )
1#
#2090
0#
#2095
b10010000 "
b10010000 &
b10010000 '
b10000010101 !
b10000010101 (
b10000010101 )
1#
#2100
0#
#2105
b10100010 "
b10100010 &
b10100010 '
b10000011010 !
b10000011010 (
b10000011010 )
1#
#2110
0#
#2115
b10110100 "
b10110100 &
b10110100 '
b10000011111 !
b10000011111 (
b10000011111 )
1#
#2120
0#
#2125
b11000110 "
b11000110 &
b11000110 '
b10000100100 !
b10000100100 (
b10000100100 )
1#
#2130
0#
#2135
b11011000 "
b11011000 &
b11011000 '
b10000101001 !
b10000101001 (
b10000101001 )
1#
#2140
0#
#2145
b11101010 "
b11101010 &
b11101010 '
b10000101110 !
b10000101110 (
b10000101110 )
1#
#2150
0#
#2155
b11111100 "
b11111100 &
b11111100 '
b10000110011 !
b10000110011 (
b10000110011 )
1#
#2160
0#
#2165
b100001110 "
b100001110 &
b100001110 '
b10000111000 !
b10000111000 (
b10000111000 )
1#
#2170
0#
#2175
b100100000 "
b100100000 &
b100100000 '
b10000111101 !
b10000111101 (
b10000111101 )
1#
#2180
0#
#2185
b100110010 "
b100110010 &
b100110010 '
b10001000010 !
b10001000010 (
b10001000010 )
1#
#2190
0#
#2195
b101000100 "
b101000100 &
b101000100 '
b10001000111 !
b10001000111 (
b10001000111 )
1#
#2200
0#
#2205
b101010110 "
b101010110 &
b101010110 '
b10001001100 !
b10001001100 (
b10001001100 )
1#
#2210
0#
#2215
b101101000 "
b101101000 &
b101101000 '
b10001010001 !
b10001010001 (
b10001010001 )
1#
#2220
0#
#2225
b101111010 "
b101111010 &
b101111010 '
b10001010110 !
b10001010110 (
b10001010110 )
1#
#2230
0#
#2235
b110001100 "
b110001100 &
b110001100 '
b10001011011 !
b10001011011 (
b10001011011 )
1#
#2240
0#
#2245
b110011110 "
b110011110 &
b110011110 '
b10001100000 !
b10001100000 (
b10001100000 )
1#
#2250
0#
#2255
b110110000 "
b110110000 &
b110110000 '
b10001100101 !
b10001100101 (
b10001100101 )
1#
#2260
0#
#2265
b111000010 "
b111000010 &
b111000010 '
b10001101010 !
b10001101010 (
b10001101010 )
1#
#2270
0#
#2275
b111010100 "
b111010100 &
b111010100 '
b10001101111 !
b10001101111 (
b10001101111 )
1#
#2280
0#
#2285
b111100110 "
b111100110 &
b111100110 '
b10001110100 !
b10001110100 (
b10001110100 )
1#
#2290
0#
#2295
b111111000 "
b111111000 &
b111111000 '
b10001111001 !
b10001111001 (
b10001111001 )
1#
#2300
0#
#2305
b1010 "
b1010 &
b1010 '
b10001111110 !
b10001111110 (
b10001111110 )
1#
#2310
0#
#2315
b11100 "
b11100 &
b11100 '
b10010000011 !
b10010000011 (
b10010000011 )
1#
#2320
0#
#2325
b101110 "
b101110 &
b101110 '
b10010001000 !
b10010001000 (
b10010001000 )
1#
#2330
0#
#2335
b1000000 "
b1000000 &
b1000000 '
b10010001101 !
b10010001101 (
b10010001101 )
1#
#2340
0#
#2345
b1010010 "
b1010010 &
b1010010 '
b10010010010 !
b10010010010 (
b10010010010 )
1#
#2350
0#
#2355
b1100100 "
b1100100 &
b1100100 '
b10010010111 !
b10010010111 (
b10010010111 )
1#
#2360
0#
#2365
b1110110 "
b1110110 &
b1110110 '
b10010011100 !
b10010011100 (
b10010011100 )
1#
#2370
0#
#2375
b10001000 "
b10001000 &
b10001000 '
b10010100001 !
b10010100001 (
b10010100001 )
1#
#2380
0#
#2385
b10011010 "
b10011010 &
b10011010 '
b10010100110 !
b10010100110 (
b10010100110 )
1#
#2390
0#
#2395
b10101100 "
b10101100 &
b10101100 '
b10010101011 !
b10010101011 (
b10010101011 )
1#
#2400
0#
#2405
b10111110 "
b10111110 &
b10111110 '
b10010110000 !
b10010110000 (
b10010110000 )
1#
#2410
0#
#2415
b11010000 "
b11010000 &
b11010000 '
b10010110101 !
b10010110101 (
b10010110101 )
1#
#2420
0#
#2425
b11100010 "
b11100010 &
b11100010 '
b10010111010 !
b10010111010 (
b10010111010 )
1#
#2430
0#
#2435
b11110100 "
b11110100 &
b11110100 '
b10010111111 !
b10010111111 (
b10010111111 )
1#
#2440
0#
#2445
b100000110 "
b100000110 &
b100000110 '
b10011000100 !
b10011000100 (
b10011000100 )
1#
#2450
0#
#2455
b100011000 "
b100011000 &
b100011000 '
b10011001001 !
b10011001001 (
b10011001001 )
1#
#2460
0#
#2465
b100101010 "
b100101010 &
b100101010 '
b10011001110 !
b10011001110 (
b10011001110 )
1#
#2470
0#
